setup.py
pyzopfli/__init__.py
pyzopfli/blocksplitter.c
pyzopfli/cache.c
pyzopfli/deflate.c
pyzopfli/hash.c
pyzopfli/katajainen.c
pyzopfli/lz77.c
pyzopfli/squeeze.c
pyzopfli/tree.c
pyzopfli/util.c
pyzopfli/zlib.py
pyzopfli/zopflimodule.c
pyzopfli.egg-info/PKG-INFO
pyzopfli.egg-info/SOURCES.txt
pyzopfli.egg-info/dependency_links.txt
pyzopfli.egg-info/top_level.txt
pyzopfli.egg-info/zip-safe
test/test_gzip.py
test/test_support.py
test/test_zipfile.py
test/test_zlib.py