Metadata-Version: 1.1
Name: pyzopfli
Version: 0.1.0
Summary: Zopfli module for python
Home-page: https://github.com/Scondo/pyzopfli
Author: Pavel Zlatovratsky (Scondo)
Author-email: scondo@mail.ru
License: ASL
Platform: UNKNOWN
Classifier: Intended Audience :: Developers
Classifier: License :: OSI Approved :: Apache Software License
Classifier: Programming Language :: Python :: Implementation :: CPython
Classifier: Topic :: System :: Archiving :: Compression
